README.rst
setup.py
deviantart/__init__.py
deviantart/api.py
deviantart/comment.py
deviantart/deviation.py
deviantart/message.py
deviantart/status.py
deviantart/user.py
deviantart.egg-info/PKG-INFO
deviantart.egg-info/SOURCES.txt
deviantart.egg-info/dependency_links.txt
deviantart.egg-info/requires.txt
deviantart.egg-info/top_level.txt