Metadata-Version: 1.0
Name: deviantart
Version: 0.1.5
Summary: A Python wrapper for the DeviantArt API
Home-page: https://github.com/neighbordog/deviantart
Author: Kevin Eichhorn
Author-email: kevineichhorn@me.com
License: MIT
Platform: UNKNOWN
